fpga_based_cnn_accelelrator/fpga_based_cnn_accelelrator.srcs/sources_1/new/conv2_buf.v
module conv2_buf #(
	parameter integer WIDTH      = 12,
	parameter integer HEIGHT     = 12,
	parameter integer DATA_BITS  = 12,
  parameter integer FILTERSIZE = 5
)(
	input  wire                 clk,
	input  wire                 rst_n,
	input  wire                 valid_in,
	input  wire [DATA_BITS-1:0] data_in,

	output reg  [DATA_BITS-1:0] data_out_0,
	output reg  [DATA_BITS-1:0] data_out_1,
	output reg  [DATA_BITS-1:0] data_out_2,
	output reg  [DATA_BITS-1:0] data_out_3,
	output reg  [DATA_BITS-1:0] data_out_4,
	output reg  [DATA_BITS-1:0] data_out_5,
	output reg  [DATA_BITS-1:0] data_out_6,
	output reg  [DATA_BITS-1:0] data_out_7,
	output reg  [DATA_BITS-1:0] data_out_8,
	output reg  [DATA_BITS-1:0] data_out_9,
	output reg  [DATA_BITS-1:0] data_out_10,
	output reg  [DATA_BITS-1:0] data_out_11,
	output reg  [DATA_BITS-1:0] data_out_12,
	output reg  [DATA_BITS-1:0] data_out_13,
	output reg  [DATA_BITS-1:0] data_out_14,
	output reg  [DATA_BITS-1:0] data_out_15,
	output reg  [DATA_BITS-1:0] data_out_16,
	output reg  [DATA_BITS-1:0] data_out_17,
	output reg  [DATA_BITS-1:0] data_out_18,
	output reg  [DATA_BITS-1:0] data_out_19,
	output reg  [DATA_BITS-1:0] data_out_20,
	output reg  [DATA_BITS-1:0] data_out_21,
	output reg  [DATA_BITS-1:0] data_out_22,
	output reg  [DATA_BITS-1:0] data_out_23,
	output reg  [DATA_BITS-1:0] data_out_24,

	output reg                  valid_out_buf
);

	// Circular buffer holding the most recent 5 rows (12 * 5) pixels.

	reg [DATA_BITS-1:0] buffer [0:WIDTH*FILTERSIZE-1];

	reg [DATA_BITS-1:0] buf_idx;          

	reg [4:0]           w_idx;            
	reg [4:0]           h_idx;   

	reg [2:0]           buf_flag;   

	reg                 state;            

	integer i;

	always @(posedge clk) begin
		if (~rst_n) begin
			for (i = 0; i <= WIDTH * FILTERSIZE - 1; i = i + 1) begin
					buffer[i] <= {DATA_BITS{1'b0}};
			end

			buf_idx       <= {DATA_BITS{1'b0}};
			w_idx         <= 5'b0;
			h_idx         <= 5'b0;
			buf_flag      <= 3'b0;
			state         <= 1'b0;
			valid_out_buf <= 1'b0;

			data_out_0    <= {DATA_BITS{1'b0}};
			data_out_1    <= {DATA_BITS{1'b0}};
			data_out_2    <= {DATA_BITS{1'b0}};
			data_out_3    <= {DATA_BITS{1'b0}};
			data_out_4    <= {DATA_BITS{1'b0}};
			data_out_5    <= {DATA_BITS{1'b0}};
			data_out_6    <= {DATA_BITS{1'b0}};
			data_out_7    <= {DATA_BITS{1'b0}};
			data_out_8    <= {DATA_BITS{1'b0}};
			data_out_9    <= {DATA_BITS{1'b0}};
			data_out_10   <= {DATA_BITS{1'b0}};
			data_out_11   <= {DATA_BITS{1'b0}};
			data_out_12   <= {DATA_BITS{1'b0}};
			data_out_13   <= {DATA_BITS{1'b0}};
			data_out_14   <= {DATA_BITS{1'b0}};
			data_out_15   <= {DATA_BITS{1'b0}};
			data_out_16   <= {DATA_BITS{1'b0}};
			data_out_17   <= {DATA_BITS{1'b0}};
			data_out_18   <= {DATA_BITS{1'b0}};
			data_out_19   <= {DATA_BITS{1'b0}};
			data_out_20   <= {DATA_BITS{1'b0}};
			data_out_21   <= {DATA_BITS{1'b0}};
			data_out_22   <= {DATA_BITS{1'b0}};
			data_out_23   <= {DATA_BITS{1'b0}};
			data_out_24   <= {DATA_BITS{1'b0}};
		end else begin
			if (valid_in) begin
				buf_idx <= buf_idx + 1'b1;

				// Write the incoming pixel data into circular buffer

				if (buf_idx == WIDTH * FILTERSIZE - 1) begin
					buf_idx <= {DATA_BITS{1'b0}};
				end

				buffer[buf_idx] <= data_in;

				
				// Starting stream after the buffer is completely filled.

				if (!state) begin
						if (buf_idx == WIDTH * FILTERSIZE - 1) begin
								state <= 1'b1;
						end
				end else begin
					w_idx <= w_idx + 1'b1;

					// Determine valid region: window is valid for columns 0..7

					if (w_idx == 0) begin
						valid_out_buf <= 1'b1;                     
					end else if (w_idx == WIDTH - FILTERSIZE + 1)
						valid_out_buf <= 1'b0;                     

					if (w_idx == WIDTH - 1) begin                  // end of a row
						buf_flag      <= buf_flag + 1'b1;
						
						if (buf_flag == FILTERSIZE - 1) begin
							buf_flag    <= 3'b0;
						end

						w_idx         <= 5'b0;

						if (h_idx == HEIGHT - FILTERSIZE) begin    // last row of windows
								h_idx     <= 5'b0;
								state     <= 1'b0;                      // processing finished
						end 
						h_idx         <= h_idx + 1'b1;
						
					end

					if (buf_flag == 3'd0) begin

						// Window rows: buffer rows 0,1,2,3,4 (relative to current write)

						data_out_0  <= buffer[w_idx                ];
						data_out_1  <= buffer[w_idx             + 1];
						data_out_2  <= buffer[w_idx             + 2];
						data_out_3  <= buffer[w_idx             + 3];
						data_out_4  <= buffer[w_idx             + 4];

						data_out_5  <= buffer[w_idx + WIDTH        ];
						data_out_6  <= buffer[w_idx + WIDTH     + 1];
						data_out_7  <= buffer[w_idx + WIDTH     + 2];
						data_out_8  <= buffer[w_idx + WIDTH     + 3];
						data_out_9  <= buffer[w_idx + WIDTH     + 4];

						data_out_10 <= buffer[w_idx + WIDTH * 2    ];
						data_out_11 <= buffer[w_idx + WIDTH * 2 + 1];
						data_out_12 <= buffer[w_idx + WIDTH * 2 + 2];
						data_out_13 <= buffer[w_idx + WIDTH * 2 + 3];
						data_out_14 <= buffer[w_idx + WIDTH * 2 + 4];

						data_out_15 <= buffer[w_idx + WIDTH * 3    ];
						data_out_16 <= buffer[w_idx + WIDTH * 3 + 1];
						data_out_17 <= buffer[w_idx + WIDTH * 3 + 2];
						data_out_18 <= buffer[w_idx + WIDTH * 3 + 3];
						data_out_19 <= buffer[w_idx + WIDTH * 3 + 4];

						data_out_20 <= buffer[w_idx + WIDTH * 4    ];
						data_out_21 <= buffer[w_idx + WIDTH * 4 + 1];
						data_out_22 <= buffer[w_idx + WIDTH * 4 + 2];
						data_out_23 <= buffer[w_idx + WIDTH * 4 + 3];
						data_out_24 <= buffer[w_idx + WIDTH * 4 + 4];

					end else if (buf_flag == 3'd1) begin

						// Window rows: buffer rows 1,2,3,4,0 (circular shift)

						data_out_0  <= buffer[w_idx + WIDTH        ];
						data_out_1  <= buffer[w_idx + WIDTH     + 1];
						data_out_2  <= buffer[w_idx + WIDTH     + 2];
						data_out_3  <= buffer[w_idx + WIDTH     + 3];
						data_out_4  <= buffer[w_idx + WIDTH     + 4];

						data_out_5  <= buffer[w_idx + WIDTH * 2    ];
						data_out_6  <= buffer[w_idx + WIDTH * 2 + 1];
						data_out_7  <= buffer[w_idx + WIDTH * 2 + 2];
						data_out_8  <= buffer[w_idx + WIDTH * 2 + 3];
						data_out_9  <= buffer[w_idx + WIDTH * 2 + 4];

						data_out_10 <= buffer[w_idx + WIDTH * 3    ];
						data_out_11 <= buffer[w_idx + WIDTH * 3 + 1];
						data_out_12 <= buffer[w_idx + WIDTH * 3 + 2];
						data_out_13 <= buffer[w_idx + WIDTH * 3 + 3];
						data_out_14 <= buffer[w_idx + WIDTH * 3 + 4];

						data_out_15 <= buffer[w_idx + WIDTH * 4    ];
						data_out_16 <= buffer[w_idx + WIDTH * 4 + 1];
						data_out_17 <= buffer[w_idx + WIDTH * 4 + 2];
						data_out_18 <= buffer[w_idx + WIDTH * 4 + 3];
						data_out_19 <= buffer[w_idx + WIDTH * 4 + 4];
						
						data_out_20 <= buffer[w_idx                ];
						data_out_21 <= buffer[w_idx             + 1];
						data_out_22 <= buffer[w_idx             + 2];
						data_out_23 <= buffer[w_idx             + 3];
						data_out_24 <= buffer[w_idx             + 4];

					end else if (buf_flag == 3'd2) begin

						// Window rows: buffer rows 2,3,4,0,1

						data_out_0  <= buffer[w_idx + WIDTH * 2   ];
						data_out_1  <= buffer[w_idx + WIDTH * 2 + 1];
						data_out_2  <= buffer[w_idx + WIDTH * 2 + 2];
						data_out_3  <= buffer[w_idx + WIDTH * 2 + 3];
						data_out_4  <= buffer[w_idx + WIDTH * 2 + 4];

						data_out_5  <= buffer[w_idx + WIDTH * 3    ];
						data_out_6  <= buffer[w_idx + WIDTH * 3 + 1];
						data_out_7  <= buffer[w_idx + WIDTH * 3 + 2];
						data_out_8  <= buffer[w_idx + WIDTH * 3 + 3];
						data_out_9  <= buffer[w_idx + WIDTH * 3 + 4];

						data_out_10 <= buffer[w_idx + WIDTH * 4    ];
						data_out_11 <= buffer[w_idx + WIDTH * 4 + 1];
						data_out_12 <= buffer[w_idx + WIDTH * 4 + 2];
						data_out_13 <= buffer[w_idx + WIDTH * 4 + 3];
						data_out_14 <= buffer[w_idx + WIDTH * 4 + 4];

						data_out_15 <= buffer[w_idx                ];
						data_out_16 <= buffer[w_idx             + 1];
						data_out_17 <= buffer[w_idx             + 2];
						data_out_18 <= buffer[w_idx             + 3];
						data_out_19 <= buffer[w_idx             + 4];

						data_out_20 <= buffer[w_idx + WIDTH        ];
						data_out_21 <= buffer[w_idx + WIDTH     + 1];
						data_out_22 <= buffer[w_idx + WIDTH     + 2];
						data_out_23 <= buffer[w_idx + WIDTH     + 3];
						data_out_24 <= buffer[w_idx + WIDTH     + 4];

					end else if (buf_flag == 3'd3) begin

						// Window rows: buffer rows 3,4,0,1,2

						data_out_0  <= buffer[w_idx + WIDTH * 3    ];
						data_out_1  <= buffer[w_idx + WIDTH * 3 + 1];
						data_out_2  <= buffer[w_idx + WIDTH * 3 + 2];
						data_out_3  <= buffer[w_idx + WIDTH * 3 + 3];
						data_out_4  <= buffer[w_idx + WIDTH * 3 + 4];

						data_out_5  <= buffer[w_idx + WIDTH * 4    ];
						data_out_6  <= buffer[w_idx + WIDTH * 4 + 1];
						data_out_7  <= buffer[w_idx + WIDTH * 4 + 2];
						data_out_8  <= buffer[w_idx + WIDTH * 4 + 3];
						data_out_9  <= buffer[w_idx + WIDTH * 4 + 4];

						data_out_10 <= buffer[w_idx                ];
						data_out_11 <= buffer[w_idx             + 1];
						data_out_12 <= buffer[w_idx             + 2];
						data_out_13 <= buffer[w_idx             + 3];
						data_out_14 <= buffer[w_idx             + 4];

						data_out_15 <= buffer[w_idx + WIDTH        ];
						data_out_16 <= buffer[w_idx + WIDTH     + 1];
						data_out_17 <= buffer[w_idx + WIDTH     + 2];
						data_out_18 <= buffer[w_idx + WIDTH     + 3];
						data_out_19 <= buffer[w_idx + WIDTH     + 4];

						data_out_20 <= buffer[w_idx + WIDTH * 2    ];
						data_out_21 <= buffer[w_idx + WIDTH * 2 + 1];
						data_out_22 <= buffer[w_idx + WIDTH * 2 + 2];
						data_out_23 <= buffer[w_idx + WIDTH * 2 + 3];
						data_out_24 <= buffer[w_idx + WIDTH * 2 + 4];

					end else begin 

						// Window rows: buffer rows 4,0,1,2,3

						data_out_0  <= buffer[w_idx + WIDTH * 4    ];
						data_out_1  <= buffer[w_idx + WIDTH * 4 + 1];
						data_out_2  <= buffer[w_idx + WIDTH * 4 + 2];
						data_out_3  <= buffer[w_idx + WIDTH * 4 + 3];
						data_out_4  <= buffer[w_idx + WIDTH * 4 + 4];

						data_out_5  <= buffer[w_idx                ];
						data_out_6  <= buffer[w_idx             + 1];
						data_out_7  <= buffer[w_idx             + 2];
						data_out_8  <= buffer[w_idx             + 3];
						data_out_9  <= buffer[w_idx             + 4];

						data_out_10 <= buffer[w_idx + WIDTH        ];
						data_out_11 <= buffer[w_idx + WIDTH     + 1];
						data_out_12 <= buffer[w_idx + WIDTH     + 2];
						data_out_13 <= buffer[w_idx + WIDTH     + 3];
						data_out_14 <= buffer[w_idx + WIDTH     + 4];

						data_out_15 <= buffer[w_idx + WIDTH * 2    ];
						data_out_16 <= buffer[w_idx + WIDTH * 2 + 1];
						data_out_17 <= buffer[w_idx + WIDTH * 2 + 2];
						data_out_18 <= buffer[w_idx + WIDTH * 2 + 3];
						data_out_19 <= buffer[w_idx + WIDTH * 2 + 4];

						data_out_20 <= buffer[w_idx + WIDTH * 3    ];
						data_out_21 <= buffer[w_idx + WIDTH * 3 + 1];
						data_out_22 <= buffer[w_idx + WIDTH * 3 + 2];
						data_out_23 <= buffer[w_idx + WIDTH * 3 + 3];
						data_out_24 <= buffer[w_idx + WIDTH * 3 + 4];
					end
				end
			end
		end
	end

endmodule

fpga_based_cnn_accelelrator/fpga_based_cnn_accelelrator.srcs/sim_1/new/tb_conv2_buf.sv
module tb_conv2_buf;

  parameter integer WIDTH      = 12;
  parameter integer HEIGHT     = 12;
  parameter integer DATA_BITS  = 12;
  parameter integer FILTERSIZE = 5;

  reg clk;
  reg rst_n;

  reg valid_in;
  reg [DATA_BITS-1:0] data_in;

  wire [DATA_BITS-1:0] data_out_0;
  wire [DATA_BITS-1:0] data_out_1;
  wire [DATA_BITS-1:0] data_out_2;
  wire [DATA_BITS-1:0] data_out_3;
  wire [DATA_BITS-1:0] data_out_4;
  wire [DATA_BITS-1:0] data_out_5;
  wire [DATA_BITS-1:0] data_out_6;
  wire [DATA_BITS-1:0] data_out_7;
  wire [DATA_BITS-1:0] data_out_8;
  wire [DATA_BITS-1:0] data_out_9;
  wire [DATA_BITS-1:0] data_out_10;
  wire [DATA_BITS-1:0] data_out_11;
  wire [DATA_BITS-1:0] data_out_12;
  wire [DATA_BITS-1:0] data_out_13;
  wire [DATA_BITS-1:0] data_out_14;
  wire [DATA_BITS-1:0] data_out_15;
  wire [DATA_BITS-1:0] data_out_16;
  wire [DATA_BITS-1:0] data_out_17;
  wire [DATA_BITS-1:0] data_out_18;
  wire [DATA_BITS-1:0] data_out_19;
  wire [DATA_BITS-1:0] data_out_20;
  wire [DATA_BITS-1:0] data_out_21;
  wire [DATA_BITS-1:0] data_out_22;
  wire [DATA_BITS-1:0] data_out_23;
  wire [DATA_BITS-1:0] data_out_24;
  wire valid_out_buf;

  conv2_buf #(
    .WIDTH    (WIDTH),
    .HEIGHT   (HEIGHT),
    .DATA_BITS(DATA_BITS)
  ) dut (
    .clk          (clk),
    .rst_n        (rst_n),
    .valid_in     (valid_in),
    .data_in      (data_in),
    .data_out_0   (data_out_0),
    .data_out_1   (data_out_1),
    .data_out_2   (data_out_2),
    .data_out_3   (data_out_3),
    .data_out_4   (data_out_4),
    .data_out_5   (data_out_5),
    .data_out_6   (data_out_6),
    .data_out_7   (data_out_7),
    .data_out_8   (data_out_8),
    .data_out_9   (data_out_9),
    .data_out_10  (data_out_10),
    .data_out_11  (data_out_11),
    .data_out_12  (data_out_12),
    .data_out_13  (data_out_13),
    .data_out_14  (data_out_14),
    .data_out_15  (data_out_15),
    .data_out_16  (data_out_16),
    .data_out_17  (data_out_17),
    .data_out_18  (data_out_18),
    .data_out_19  (data_out_19),
    .data_out_20  (data_out_20),
    .data_out_21  (data_out_21),
    .data_out_22  (data_out_22),
    .data_out_23  (data_out_23),
    .data_out_24  (data_out_24),
    .valid_out_buf(valid_out_buf)
  );

  // Clock generation
  always #5 clk = ~clk;

  // Image storage
  reg [DATA_BITS-1:0] image [0:HEIGHT-1][0:WIDTH-1];
  integer row, col;
  integer pixel_cnt;   // number of pixels sent so far
  integer valid_cnt;   // number of valid_out_buf pulses seen
  integer error_cnt;   // number of mismatches

  // Expected window (row‑major order)
  reg [DATA_BITS-1:0] expected [0:FILTERSIZE*FILTERSIZE-1];

  initial begin
    clk = 0;
    rst_n = 0;
    valid_in = 0;
    data_in = 0;
    pixel_cnt = 0;
    valid_cnt = 0;
    error_cnt = 0;

    // Dump waveform
    $dumpfile("tb_conv2_buf.vcd");
    $dumpvars(0, tb_conv2_buf);

    #20 rst_n = 1;
    #10;

    // Feed entire 12x12 image
    for (row = 0; row < HEIGHT; row = row + 1) begin
      for (col = 0; col < WIDTH; col = col + 1) begin
        @(posedge clk);
        valid_in = 1;
        data_in = row * WIDTH + col;   // simple pattern
        image[row][col] = data_in;
        pixel_cnt = pixel_cnt + 1;
      end
    end

    @(posedge clk);
    valid_in = 0;
    repeat (20) @(posedge clk);   // wait for any remaining outputs

    $display("Total valid outputs: %0d", valid_cnt);
    if (valid_cnt == (HEIGHT - FILTERSIZE + 1) * (WIDTH - FILTERSIZE + 1))
      $display("Valid count OK");
    else
      $display("ERROR: Expected %0d valid outputs",
               (HEIGHT - FILTERSIZE + 1) * (WIDTH - FILTERSIZE + 1));

    if (error_cnt == 0)
      $display("TEST PASSED");
    else
      $display("TEST FAILED with %0d errors", error_cnt);

    $finish;
  end

  // Check outputs on the falling edge to avoid race conditions
  always @(negedge clk) begin
    if (rst_n && valid_out_buf) begin
      valid_cnt = valid_cnt + 1;

      // Determine window position (top‑left row and column)
      // First valid output occurs after the buffer is full:
      // pixel_cnt counts total pixels sent. The first streaming pixel is
      // pixel_cnt = WIDTH*FILTERSIZE + 1 (when the first pixel of the 6th row arrives)
      if (pixel_cnt >= WIDTH * FILTERSIZE + 1) begin
        integer m, w, h;
        m = pixel_cnt - (WIDTH * FILTERSIZE + 1);   // 0 at first streaming pixel
        w = m % WIDTH;
        h = m / WIDTH;

        // Build expected window from stored image
        for (int i = 0; i < FILTERSIZE; i = i + 1) begin
          for (int j = 0; j < FILTERSIZE; j = j + 1) begin
            expected[i * FILTERSIZE + j] = image[h + i][w + j];
          end
        end

        compare_outputs;
      end
    end
  end

  task compare_outputs;
    begin
      if (data_out_0  !== expected[ 0]) error( 0, expected[ 0], data_out_0 );
      if (data_out_1  !== expected[ 1]) error( 1, expected[ 1], data_out_1 );
      if (data_out_2  !== expected[ 2]) error( 2, expected[ 2], data_out_2 );
      if (data_out_3  !== expected[ 3]) error( 3, expected[ 3], data_out_3 );
      if (data_out_4  !== expected[ 4]) error( 4, expected[ 4], data_out_4 );
      if (data_out_5  !== expected[ 5]) error( 5, expected[ 5], data_out_5 );
      if (data_out_6  !== expected[ 6]) error( 6, expected[ 6], data_out_6 );
      if (data_out_7  !== expected[ 7]) error( 7, expected[ 7], data_out_7 );
      if (data_out_8  !== expected[ 8]) error( 8, expected[ 8], data_out_8 );
      if (data_out_9  !== expected[ 9]) error( 9, expected[ 9], data_out_9 );
      if (data_out_10 !== expected[10]) error(10, expected[10], data_out_10);
      if (data_out_11 !== expected[11]) error(11, expected[11], data_out_11);
      if (data_out_12 !== expected[12]) error(12, expected[12], data_out_12);
      if (data_out_13 !== expected[13]) error(13, expected[13], data_out_13);
      if (data_out_14 !== expected[14]) error(14, expected[14], data_out_14);
      if (data_out_15 !== expected[15]) error(15, expected[15], data_out_15);
      if (data_out_16 !== expected[16]) error(16, expected[16], data_out_16);
      if (data_out_17 !== expected[17]) error(17, expected[17], data_out_17);
      if (data_out_18 !== expected[18]) error(18, expected[18], data_out_18);
      if (data_out_19 !== expected[19]) error(19, expected[19], data_out_19);
      if (data_out_20 !== expected[20]) error(20, expected[20], data_out_20);
      if (data_out_21 !== expected[21]) error(21, expected[21], data_out_21);
      if (data_out_22 !== expected[22]) error(22, expected[22], data_out_22);
      if (data_out_23 !== expected[23]) error(23, expected[23], data_out_23);
      if (data_out_24 !== expected[24]) error(24, expected[24], data_out_24);
    end
  endtask

  task error(input integer idx, input [DATA_BITS-1:0] exp, act);
    begin
      $display("ERROR at valid_out %0d, output %0d: expected %0d, got %0d",
               valid_cnt, idx, exp, act);
      error_cnt = error_cnt + 1;
    end
  endtask

endmodule

fpga_based_cnn_v20/fpga_based_cnn_v20.sim/sim_1/behav/xsim/tb_conv2_buf.vcd
$date
   Sat Mar 21 13:51:02 2026
$end
$version
  2020.2
$end
$timescale
  1ps
$end
$scope module tb_conv2_buf $end
$var reg 1 ! clk $end
$var reg 1 " rst_n $end
$var reg 1 # valid_in $end
$var reg 12 $ data_in [11:0] $end
$var wire 12 % data_out_0 [11:0] $end
$var wire 12 & data_out_1 [11:0] $end
$var wire 12 ' data_out_2 [11:0] $end
$var wire 12 ( data_out_3 [11:0] $end
$var wire 12 ) data_out_4 [11:0] $end
$var wire 12 * data_out_5 [11:0] $end
$var wire 12 + data_out_6 [11:0] $end
$var wire 12 , data_out_7 [11:0] $end
$var wire 12 - data_out_8 [11:0] $end
$var wire 12 . data_out_9 [11:0] $end
$var wire 12 / data_out_10 [11:0] $end
$var wire 12 0 data_out_11 [11:0] $end
$var wire 12 1 data_out_12 [11:0] $end
$var wire 12 2 data_out_13 [11:0] $end
$var wire 12 3 data_out_14 [11:0] $end
$var wire 12 4 data_out_15 [11:0] $end
$var wire 12 5 data_out_16 [11:0] $end
$var wire 12 6 data_out_17 [11:0] $end
$var wire 12 7 data_out_18 [11:0] $end
$var wire 12 8 data_out_19 [11:0] $end
$var wire 12 9 data_out_20 [11:0] $end
$var wire 12 : data_out_21 [11:0] $end
$var wire 12 ; data_out_22 [11:0] $end
$var wire 12 < data_out_23 [11:0] $end
$var wire 12 = data_out_24 [11:0] $end
$var wire 1 > valid_out_buf $end
$var integer 32 ? row $end
$var integer 32 @ col $end
$var integer 32 A pixel_cnt $end
$var integer 32 B valid_cnt $end
$var integer 32 C error_cnt $end
$var parameter 0 D WIDTH $end
$var parameter 0 E HEIGHT $end
$var parameter 0 F DATA_BITS $end
$var parameter 0 G FILTERSIZE $end
$scope module dut $end
$var wire 1 H clk $end
$var wire 1 I rst_n $end
$var wire 1 J valid_in $end
$var wire 12 K data_in [11:0] $end
$var reg 12 L data_out_0 [11:0] $end
$var reg 12 M data_out_1 [11:0] $end
$var reg 12 N data_out_2 [11:0] $end
$var reg 12 O data_out_3 [11:0] $end
$var reg 12 P data_out_4 [11:0] $end
$var reg 12 Q data_out_5 [11:0] $end
$var reg 12 R data_out_6 [11:0] $end
$var reg 12 S data_out_7 [11:0] $end
$var reg 12 T data_out_8 [11:0] $end
$var reg 12 U data_out_9 [11:0] $end
$var reg 12 V data_out_10 [11:0] $end
$var reg 12 W data_out_11 [11:0] $end
$var reg 12 X data_out_12 [11:0] $end
$var reg 12 Y data_out_13 [11:0] $end
$var reg 12 Z data_out_14 [11:0] $end
$var reg 12 [ data_out_15 [11:0] $end
$var reg 12 \ data_out_16 [11:0] $end
$var reg 12 ] data_out_17 [11:0] $end
$var reg 12 ^ data_out_18 [11:0] $end
$var reg 12 _ data_out_19 [11:0] $end
$var reg 12 ` data_out_20 [11:0] $end
$var reg 12 a data_out_21 [11:0] $end
$var reg 12 b data_out_22 [11:0] $end
$var reg 12 c data_out_23 [11:0] $end
$var reg 12 d data_out_24 [11:0] $end
$var reg 1 e valid_out_buf $end
$var reg 12 f buf_idx [11:0] $end
$var reg 5 g w_idx [4:0] $end
$var reg 5 h h_idx [4:0] $end
$var reg 3 i buf_flag [2:0] $end
$var reg 1 j state $end
$var integer 32 k i $end
$var parameter 0 l WIDTH $end
$var parameter 0 m HEIGHT $end
$var parameter 0 n DATA_BITS $end
$var parameter 0 o FILTERSIZE $end
$upscope $end
$scope begin Block146_4 $end
$var integer 32 p m $end
$var integer 32 q w $end
$var integer 32 r h $end
$scope begin Block153_5 $end
$var reg 32 s i $end
$scope begin Block154_6 $end
$var reg 32 t j $end
$upscope $end
$upscope $end
$upscope $end
$scope task compare_outputs $end
$upscope $end
$scope task error $end
$var integer 32 u idx $end
$var reg 12 v exp [11:0] $end
$var reg 12 w act [11:0] $end
$upscope $end
$upscope $end
$enddefinitions $end
#0
$dumpvars
0!
0"
0#
b0 $
bx %
bx &
bx '
bx (
bx )
bx *
bx +
bx ,
bx -
bx .
bx /
bx 0
bx 1
bx 2
bx 3
bx 4
bx 5
bx 6
bx 7
bx 8
bx 9
bx :
bx ;
bx <
bx =
x>
bx ?
bx @
b0 A
b0 B
b0 C
b1100 D
b1100 E
b1100 F
b101 G
0H
0I
0J
b0 K
bx L
bx M
bx N
bx O
bx P
bx Q
bx R
bx S
bx T
bx U
bx V
bx W
bx X
bx Y
bx Z
bx [
bx \
bx ]
bx ^
bx _
bx `
bx a
bx b
bx c
bx d
xe
bx f
bx g
bx h
bx i
xj
bx k
b1100 l
b1100 m
b1100 n
b101 o
bx p
bx q
bx r
b0 s
b0 t
bx u
bx v
bx w
$end
#5000
1!
b0 %
b0 &
b0 '
b0 (
b0 )
b0 *
b0 +
b0 ,
b0 -
b0 .
b0 /
b0 0
b0 1
b0 2
b0 3
b0 4
b0 5
b0 6
b0 7
b0 8
b0 9
b0 :
b0 ;
b0 <
b0 =
0>
1H
b0 L
b0 M
b0 N
b0 O
b0 P
b0 Q
b0 R
b0 S
b0 T
b0 U
b0 V
b0 W
b0 X
b0 Y
b0 Z
b0 [
b0 \
b0 ]
b0 ^
b0 _
b0 `
b0 a
b0 b
b0 c
b0 d
0e
b0 f
b0 g
b0 h
b0 i
0j
b111100 k
#10000
0!
0H
#15000
1!
1H
b111100 k
#20000
0!
1"
0H
1I
#25000
1!
1H
#30000
0!
b0 ?
b0 @
0H
#35000
1!
1#
b0 $
b1 @
b1 A
1H
1J
b1 f
#40000
0!
0H
#45000
1!
b1 $
b10 @
b10 A
1H
b1 K
b10 f
#50000
0!
0H
#55000
1!
b10 $
b11 @
b11 A
1H
b10 K
b11 f
#60000
0!
0H
#65000
1!
b11 $
b100 @
b100 A
1H
b11 K
b100 f
#70000
0!
0H
#75000
1!
b100 $
b101 @
b101 A
1H
b100 K
b101 f
#80000
0!
0H
#85000
1!
b101 $
b110 @
b110 A
1H
b101 K
b110 f
#90000
0!
0H
#95000
1!
b110 $
b111 @
b111 A
1H
b110 K
b111 f
#100000
0!
0H
#105000
1!
b111 $
b1000 @
b1000 A
1H
b111 K
b1000 f
#110000
0!
0H
#115000
1!
b1000 $
b1001 @
b1001 A
1H
b1000 K
b1001 f
#120000
0!
0H
#125000
1!
b1001 $
b1010 @
b1010 A
1H
b1001 K
b1010 f
#130000
0!
0H
#135000
1!
b1010 $
b1011 @
b1011 A
1H
b1010 K
b1011 f
#140000
0!
0H
#145000
1!
b1011 $
b1 ?
b0 @
b1100 A
1H
b1011 K
b1100 f
#150000
0!
0H
#155000
1!
b1100 $
b1 @
b1101 A
1H
b1100 K
b1101 f
#160000
0!
0H
#165000
1!
b1101 $
b10 @
b1110 A
1H
b1101 K
b1110 f
#170000
0!
0H
#175000
1!
b1110 $
b11 @
b1111 A
1H
b1110 K
b1111 f
#180000
0!
0H
#185000
1!
b1111 $
b100 @
b10000 A
1H
b1111 K
b10000 f
#190000
0!
0H
#195000
1!
b10000 $
b101 @
b10001 A
1H
b10000 K
b10001 f
#200000
0!
0H
#205000
1!
b10001 $
b110 @
b10010 A
1H
b10001 K
b10010 f
#210000
0!
0H
#215000
1!
b10010 $
b111 @
b10011 A
1H
b10010 K
b10011 f
#220000
0!
0H
#225000
1!
b10011 $
b1000 @
b10100 A
1H
b10011 K
b10100 f
#230000
0!
0H
#235000
1!
b10100 $
b1001 @
b10101 A
1H
b10100 K
b10101 f
#240000
0!
0H
#245000
1!
b10101 $
b1010 @
b10110 A
1H
b10101 K
b10110 f
#250000
0!
0H
#255000
1!
b10110 $
b1011 @
b10111 A
1H
b10110 K
b10111 f
#260000
0!
0H
#265000
1!
b10111 $
b10 ?
b0 @
b11000 A
1H
b10111 K
b11000 f
#270000
0!
0H
#275000
1!
b11000 $
b1 @
b11001 A
1H
b11000 K
b11001 f
#280000
0!
0H
#285000
1!
b11001 $
b10 @
b11010 A
1H
b11001 K
b11010 f
#290000
0!
0H
#295000
1!
b11010 $
b11 @
b11011 A
1H
b11010 K
b11011 f
#300000
0!
0H
#305000
1!
b11011 $
b100 @
b11100 A
1H
b11011 K
b11100 f
#310000
0!
0H
#315000
1!
b11100 $
b101 @
b11101 A
1H
b11100 K
b11101 f
#320000
0!
0H
#325000
1!
b11101 $
b110 @
b11110 A
1H
b11101 K
b11110 f
#330000
0!
0H
#335000
1!
b11110 $
b111 @
b11111 A
1H
b11110 K
b11111 f
#340000
0!
0H
#345000
1!
b11111 $
b1000 @
b100000 A
1H
b11111 K
b100000 f
#350000
0!
0H
#355000
1!
b100000 $
b1001 @
b100001 A
1H
b100000 K
b100001 f
#360000
0!
0H
#365000
1!
b100001 $
b1010 @
b100010 A
1H
b100001 K
b100010 f
#370000
0!
0H
#375000
1!
b100010 $
b1011 @
b100011 A
1H
b100010 K
b100011 f
#380000
0!
0H
#385000
1!
b100011 $
b11 ?
b0 @
b100100 A
1H
b100011 K
b100100 f
#390000
0!
0H
#395000
1!
b100100 $
b1 @
b100101 A
1H
b100100 K
b100101 f
#400000
0!
0H
#405000
1!
b100101 $
b10 @
b100110 A
1H
b100101 K
b100110 f
#410000
0!
0H
#415000
1!
b100110 $
b11 @
b100111 A
1H
b100110 K
b100111 f
#420000
0!
0H
#425000
1!
b100111 $
b100 @
b101000 A
1H
b100111 K
b101000 f
#430000
0!
0H
#435000
1!
b101000 $
b101 @
b101001 A
1H
b101000 K
b101001 f
#440000
0!
0H
#445000
1!
b101001 $
b110 @
b101010 A
1H
b101001 K
b101010 f
#450000
0!
0H
#455000
1!
b101010 $
b111 @
b101011 A
1H
b101010 K
b101011 f
#460000
0!
0H
#465000
1!
b101011 $
b1000 @
b101100 A
1H
b101011 K
b101100 f
#470000
0!
0H
#475000
1!
b101100 $
b1001 @
b101101 A
1H
b101100 K
b101101 f
#480000
0!
0H
#485000
1!
b101101 $
b1010 @
b101110 A
1H
b101101 K
b101110 f
#490000
0!
0H
#495000
1!
b101110 $
b1011 @
b101111 A
1H
b101110 K
b101111 f
#500000
0!
0H
#505000
1!
b101111 $
b100 ?
b0 @
b110000 A
1H
b101111 K
b110000 f
#510000
0!
0H
#515000
1!
b110000 $
b1 @
b110001 A
1H
b110000 K
b110001 f
#520000
0!
0H
#525000
1!
b110001 $
b10 @
b110010 A
1H
b110001 K
b110010 f
#530000
0!
0H
