fpga_based_cnn_accelelrator/fpga_based_cnn_accelelrator.srcs/sources_1/new/test_counter.v
module test_counter (
    input clk,
    input reset,
    output reg [3:0] count
);
    always @(posedge clk or posedge reset) begin
        if (reset)
            count <= 4'b0;
        else
            count <= count + 1;
    end
endmodule

fpga_based_cnn_accelelrator/fpga_based_cnn_accelelrator.srcs/sim_1/new/tb_test_counter.v
module tb_test_counter;
    reg clk;
    reg reset;
    wire [3:0] count;

    // Instantiate the counter
    test_counter uut (
        .clk(clk),
        .reset(reset),
        .count(count)
    );

    // Generate clock (10 ns period)
    initial begin
        clk = 0;
        forever #5 clk = ~clk;
    end

    // Apply stimulus
    initial begin
        reset = 1;
        #15 reset = 0;
        #100 $finish;
    end

    // Dump waveform data
    initial begin
        $dumpfile("tb_test_counter.vcd");
        $dumpvars(0, tb_test_counter);
    end
endmodule

fpga_based_cnn_accelelrator/tb_test_counter.vcd
$date
	Thu Feb 19 17:22:49 2026
$end
$version
	Icarus Verilog
$end
$timescale
	1s
$end
$scope module tb_test_counter $end
$var wire 4 ! count [3:0] $end
$var reg 1 " clk $end
$var reg 1 # reset $end
$scope module uut $end
$var wire 1 " clk $end
$var wire 1 # reset $end
$var reg 4 $ count [3:0] $end
$upscope $end
$upscope $end
$enddefinitions $end
#0
$dumpvars
b0 $
1#
0"
b0 !
$end
#5
1"
#10
0"
#15
b1 !
b1 $
1"
0#
#20
0"
#25
b10 !
b10 $
1"
#30
0"
#35
b11 !
b11 $
1"
#40
0"
#45
b100 !
b100 $
1"
#50
0"
#55
b101 !
b101 $
1"
#60
0"
#65
b110 !
b110 $
1"
#70
0"
#75
b111 !
b111 $
1"
#80
0"
#85
b1000 !
b1000 $
1"
#90
0"
#95
b1001 !
b1001 $
1"
#100
0"
#105
b1010 !
b1010 $
1"
#110
0"
#115
b1011 !
b1011 $
1"
